[
  {
    "path": "models/gemma4-e2b-it-qat/aux.gguf",
    "format": "gguf",
    "sha256": "58c187648007cab392bd5678b87e862c3e8794017deb945feea2cf256195e96a",
    "size_bytes": 986833312,
    "verdict": "SAFE",
    "findings": [
      {
        "severity": "INFO",
        "detail": "GGUF OK (version=3, tensors~1411, kv~31)."
      }
    ]
  },
  {
    "path": "models/gemma4-e2b-it-qat/weights.gguf",
    "format": "gguf",
    "sha256": "3646b4c147cd235a44d91df1546d3b7d8e29b547dbe4e1f80856419aa455e6fd",
    "size_bytes": 3349514112,
    "verdict": "SAFE",
    "findings": [
      {
        "severity": "INFO",
        "detail": "GGUF OK (version=3, tensors~541, kv~43)."
      }
    ]
  }
]
